AUTHORS.rst
CONTRIBUTING.rst
HISTORY.rst
LICENSE
MANIFEST.in
README.rst
setup.cfg
setup.py
docs/Makefile
docs/authors.rst
docs/conf.py
docs/contributing.rst
docs/history.rst
docs/index.rst
docs/installation.rst
docs/make.bat
docs/readme.rst
docs/usage.rst
qt_aider.egg-info/PKG-INFO
qt_aider.egg-info/SOURCES.txt
qt_aider.egg-info/dependency_links.txt
qt_aider.egg-info/entry_points.txt
qt_aider.egg-info/not-zip-safe
qt_aider.egg-info/requires.txt
qt_aider.egg-info/top_level.txt
qtaider/__init__.py
qtaider/__main__.py
qtaider/application.py
qtaider/eventlet.py
qtaider/qtaider.py
qtaider/singleworld.py
qtaider/utils.py
tests/__init__.py
tests/test_qtaider.py