Metadata-Version: 1.1
Name: qt-aider
Version: 0.3.1
Summary: An extension library for Qt library
Home-page: https://github.com/starofrainnight/qt-aider
Author: Hong-She Liang
Author-email: starofrainnight@gmail.com
License: Apache Software License
Keywords: qtaider,qt-aider
Platform: UNKNOWN
Classifier: Development Status :: 3 - Alpha
Classifier: Intended Audience :: Developers
Classifier: License :: OSI Approved :: Apache Software License
Classifier: Programming Language :: Python :: 3
Classifier: Programming Language :: Python :: 3.5
Classifier: Programming Language :: Python :: 3.6
